clientapi_forgejo/__init__.py
clientapi_forgejo/api_client.py
clientapi_forgejo/api_response.py
clientapi_forgejo/configuration.py
clientapi_forgejo/exceptions.py
clientapi_forgejo/forgejo.py
clientapi_forgejo/py.typed
clientapi_forgejo/rest.py
clientapi_forgejo/api/__init__.py
clientapi_forgejo/api/activitypub_api.py
clientapi_forgejo/api/admin_api.py
clientapi_forgejo/api/issue_api.py
clientapi_forgejo/api/miscellaneous_api.py
clientapi_forgejo/api/notification_api.py
clientapi_forgejo/api/organization_api.py
clientapi_forgejo/api/package_api.py
clientapi_forgejo/api/repository_api.py
clientapi_forgejo/api/settings_api.py
clientapi_forgejo/api/user_api.py
clientapi_forgejo/models/__init__.py
clientapi_forgejo/models/access_token.py
clientapi_forgejo/models/action_task.py
clientapi_forgejo/models/action_task_response.py
clientapi_forgejo/models/action_variable.py
clientapi_forgejo/models/activity.py
clientapi_forgejo/models/activity_pub.py
clientapi_forgejo/models/add_collaborator_option.py
clientapi_forgejo/models/add_time_option.py
clientapi_forgejo/models/annotated_tag.py
clientapi_forgejo/models/annotated_tag_object.py
clientapi_forgejo/models/api_error.py
clientapi_forgejo/models/api_forbidden_error.py
clientapi_forgejo/models/api_invalid_topics_error.py
clientapi_forgejo/models/api_not_found.py
clientapi_forgejo/models/api_repo_archived_error.py
clientapi_forgejo/models/api_unauthorized_error.py
clientapi_forgejo/models/api_validation_error.py
clientapi_forgejo/models/attachment.py
clientapi_forgejo/models/blocked_user.py
clientapi_forgejo/models/branch.py
clientapi_forgejo/models/branch_protection.py
clientapi_forgejo/models/change_file_operation.py
clientapi_forgejo/models/change_files_options.py
clientapi_forgejo/models/changed_file.py
clientapi_forgejo/models/combined_status.py
clientapi_forgejo/models/comment.py
clientapi_forgejo/models/commit.py
clientapi_forgejo/models/commit_affected_files.py
clientapi_forgejo/models/commit_date_options.py
forgejo_python-1.1.1.dist-info/LICENSE
forgejo_python-1.1.1.dist-info/METADATA
forgejo_python-1.1.1.dist-info/WHEEL
forgejo_python-1.1.1.dist-info/top_level.txt
forgejo_python-1.1.1.dist-info/RECORD
